bitalu8.v
module bitalu8(
    input [7:0] a,
    input [7:0] b,
    input[2:0] sel ,
    output reg [7:0] y
);
    always @(*)begin
        case(sel)
        3'b000:y=a+b;
        3'b001:y=a-b;
        3'b010:y=a&b;
        3'b011:y=a|b;
        3'b100:y=a^b;
        3'b101:y=~a;
        3'b110:y=a<<1;
        3'b111:y=a>>1;
        default:y=8'b00000000;
        endcase
    end
endmodule

tb_bitalu8.v
module tb_8bitalu;
reg [7:0] a,b;
reg [2:0] sel;
wire [7:0] y;
 bitalu8 uut(
    .a(a),
    .b(b),
    .sel(sel),
    .y(y)
 );
 initial begin
    $dumpfile("8bitalu.vcd");
    $dumpvars(0,tb_8bitalu);
     a=8'd10; b=8'd5; sel=3'b000;
     #10;
     sel= 3'b001;
     #10;
     sel=3'b010;
     #10;
     sel=3'b011;
     #10;
     sel=3'b100;
     #10;
     sel=3'b101;
     #10;
     sel=3'b110;
     #10;
     sel=3'b111;
     #10;
     a=8'd255;b=8'd1; sel=3'b000;
     #10;
     a=8'd15;b=8'd3; sel=3'b001;
     #10;
     $finish ;
 end
endmodule

8bitalu.vcd
$date
	Sat Jun 06 16:38:54 2026
$end
$version
	Icarus Verilog
$end
$timescale
	1s
$end
$scope module tb_8bitalu $end
$var wire 8 ! y [7:0] $end
$var reg 8 " a [7:0] $end
$var reg 8 # b [7:0] $end
$var reg 3 $ sel [2:0] $end
$scope module uut $end
$var wire 8 % a [7:0] $end
$var wire 8 & b [7:0] $end
$var wire 3 ' sel [2:0] $end
$var reg 8 ( y [7:0] $end
$upscope $end
$upscope $end
$enddefinitions $end
$comment Show the parameter values. $end
$dumpall
$end
#0
$dumpvars
b1111 (
b0 '
b101 &
b1010 %
b0 $
b101 #
b1010 "
b1111 !
$end
#10
b101 !
b101 (
b1 $
b1 '
#20
b0 !
b0 (
b10 $
b10 '
#30
b1111 !
b1111 (
b11 $
b11 '
#40
b100 $
b100 '
#50
b11110101 !
b11110101 (
b101 $
b101 '
#60
b10100 !
b10100 (
b110 $
b110 '
#70
b101 !
b101 (
b111 $
b111 '
#80
b0 !
b0 (
b0 $
b0 '
b1 #
b1 &
b11111111 "
b11111111 %
#90
b1100 !
b1100 (
b1 $
b1 '
b11 #
b11 &
b1111 "
b1111 %
